drfx/__init__.py
drfx/mixins/__init__.py
drfx/mixins/viewsets.py
drfx-0.1.4.dist-info/METADATA
drfx-0.1.4.dist-info/WHEEL
drfx-0.1.4.dist-info/top_level.txt
drfx-0.1.4.dist-info/RECORD
