Metadata-Version: 2.4
Name: drfx
Version: 0.1.4
Summary: Optimized and performance Django Rest Framework Extensions
Author-email: Dmitrii <you@example.com>
License: MIT
Requires-Python: >=3.10
Requires-Dist: djangorestframework>=3.14
